tests/__init__.py
tests/test_event.py
tests/test_indicators.py
tests/test_order_handler.py
tests/test_portfolio.py
tests/test_statistics.py
tests/test_twsclient.py
tests/test_us_stock_schedule.py
tradingsystem/__init__.py
tradingsystem/common.py
tradingsystem/ib_trading_session.py
tradingsystem/simulated_trading_session.py
tradingsystem/broker/__init__.py
tradingsystem/broker/base.py
tradingsystem/broker/ib_broker.py
tradingsystem/broker/simulated_broker.py
tradingsystem/calendar/__init__.py
tradingsystem/calendar/calendar.py
tradingsystem/data/__init__.py
tradingsystem/data_handler/__init__.py
tradingsystem/data_handler/base.py
tradingsystem/data_handler/historical_bar_handler.py
tradingsystem/data_handler/ib_real_time.py
tradingsystem/data_handler/twevel_real_time.py
tradingsystem/event/__init__.py
tradingsystem/event/event.py
tradingsystem/ibapi/__init__.py
tradingsystem/ibapi/account_summary_tags.py
tradingsystem/ibapi/client.py
tradingsystem/ibapi/comm.py
tradingsystem/ibapi/commission_report.py
tradingsystem/ibapi/common.py
tradingsystem/ibapi/connection.py
tradingsystem/ibapi/contract.py
tradingsystem/ibapi/decoder.py
tradingsystem/ibapi/enum_implem.py
tradingsystem/ibapi/errors.py
tradingsystem/ibapi/execution.py
tradingsystem/ibapi/message.py
tradingsystem/ibapi/news.py
tradingsystem/ibapi/object_implem.py
tradingsystem/ibapi/order.py
tradingsystem/ibapi/order_condition.py
tradingsystem/ibapi/order_state.py
tradingsystem/ibapi/orderdecoder.py
tradingsystem/ibapi/reader.py
tradingsystem/ibapi/scanner.py
tradingsystem/ibapi/server_versions.py
tradingsystem/ibapi/softdollartier.py
tradingsystem/ibapi/tag_value.py
tradingsystem/ibapi/ticktype.py
tradingsystem/ibapi/utils.py
tradingsystem/ibapi/wrapper.py
tradingsystem/ibtws/__init__.py
tradingsystem/ibtws/contracts.py
tradingsystem/ibtws/orders.py
tradingsystem/ibtws/twsclient.py
tradingsystem/ibtws/twswrapper.py
tradingsystem/order_handler/__init__.py
tradingsystem/order_handler/base.py
tradingsystem-0.0.1.dist-info/LICENSE
tradingsystem-0.0.1.dist-info/METADATA
tradingsystem-0.0.1.dist-info/WHEEL
tradingsystem-0.0.1.dist-info/top_level.txt
tradingsystem-0.0.1.dist-info/RECORD
