Metadata-Version: 2.1
Name: tradingsystem
Version: 0.0.1
Summary: An event-driven trading system
Home-page: https://github.com/ronshen0404/tradingsystem
Author: ronshen0404
Author-email: ronshen970404@gmail.com
Classifier: Programming Language :: Python :: 3.9
Classifier: Operating System :: MacOS
Classifier: Operating System :: POSIX :: Linux
License-File: LICENSE
Requires-Dist: mysql-connector-python (>=8.0.30)
Requires-Dist: matplotlib (>=3.5.2)
Requires-Dist: numpy (>=1.23.1)
Requires-Dist: pandas (>=1.4.3)
Requires-Dist: yfinance (>=0.1.74)
